{
    "fields": {
        "name": {
            "type": "varchar",
            "required": true,
            "index": true
        },
        "status": {
            "type": "enum",
            "options": [
                "Active",
                "Inactive"
            ],
            "default": "Active",
            "style": {
                "Inactive": "info"
            },
            "audited": true
        },
        "address": {
            "type": "address"
        },
        "isAvailableForStock": {
            "type": "bool",
            "default": true,
            "index": true,
            "audited": true
        },
        "teams": {
            "type": "linkMultiple"
        },
        "description": {
            "type": "text"
        },
        "createdAt": {
            "type": "datetime",
            "readOnly": true
        },
        "modifiedAt": {
            "type": "datetime",
            "readOnly": true
        },
        "createdBy": {
            "type": "link",
            "readOnly": true
        },
        "modifiedBy": {
            "type": "link",
            "readOnly": true
        }
    },
    "links": {
        "inventoryTransactions": {
            "type": "hasMany",
            "foreign": "warehouse",
            "entity": "InventoryTransaction"
        },
        "teams": {
            "type": "hasMany",
            "entity": "Team",
            "relationName": "EntityTeam",
            "layoutRelationshipsDisabled": true
        },
        "createdBy": {
            "type": "belongsTo",
            "entity": "User"
        },
        "modifiedBy": {
            "type": "belongsTo",
            "entity": "User"
        }
    },
    "collection": {
        "sortBy": "name",
        "asc": true
    }
}
